./.gitignore
./.python-version
./PKG-INFO
./PUBLISHING.md
./README.md
./git-blame-tool.py
./git_blame_tool.py
./main.py
./pyproject.toml
./uv.lock
./.github/workflows/publish.yml
./git_blame_lake/blame.lance/_transactions/0-d13cd4f6-c09a-49eb-beb9-978171317bb7.txn
./git_blame_lake/blame.lance/_versions/1.manifest
./git_blame_lake/commits.lance/_transactions/0-7dd83fd5-d1d2-4b0b-8c7a-0507ee00f730.txn
./git_blame_lake/commits.lance/_transactions/1-4a6819cb-11d6-4eab-91a6-dfba6c662ad4.txn
./git_blame_lake/commits.lance/_transactions/1-5abbc731-8eb2-495b-933a-e2c1a36b8642.txn
./git_blame_lake/commits.lance/_versions/1.manifest
./git_blame_lake/commits.lance/_versions/2.manifest
./git_blame_lake/commits.lance/_versions/3.manifest
./git_blame_lake/commits.lance/data/d54ac8d3-1326-41f2-9304-34b5f092a96a.lance
./git_blame_lake/commits.lance/data/dd69b7b8-7730-43a3-b95d-f2933c7237ee.lance
./git_blame_lake/diffs.lance/_transactions/0-af3b9295-0b92-4d60-86d3-a343463e3325.txn
./git_blame_lake/diffs.lance/_versions/1.manifest
git_blame_search-0.1.0.dist-info/METADATA
git_blame_search-0.1.0.dist-info/WHEEL
git_blame_search-0.1.0.dist-info/entry_points.txt
git_blame_search-0.1.0.dist-info/RECORD
