Metadata-Version: 2.4
Name: git_blame_search
Version: 0.1.0
Summary: Semantic search tool for git repositories using LanceDB
Author-email: Your Name <your.email@example.com>
License: MIT
Keywords: blame,git,lancedb,search,semantic,vector
Classifier: Development Status :: 3 - Alpha
Classifier: Intended Audience :: Developers
Classifier: License :: OSI Approved :: MIT License
Classifier: Programming Language :: Python :: 3
Classifier: Programming Language :: Python :: 3.9
Classifier: Programming Language :: Python :: 3.10
Classifier: Programming Language :: Python :: 3.11
Classifier: Programming Language :: Python :: 3.12
Requires-Python: >=3.9
Requires-Dist: click>=8.0.0
Requires-Dist: flask>=3.0.0
Requires-Dist: gitpython>=3.1.0
Requires-Dist: lancedb>=0.5.0
Requires-Dist: pandas>=2.3.0
Requires-Dist: pyarrow>=14.0.0
Requires-Dist: rich>=13.0.0
Requires-Dist: sentence-transformers>=2.2.0
